odoo/addons/shopinvader_product_brand/README.rst
odoo/addons/shopinvader_product_brand/__init__.py
odoo/addons/shopinvader_product_brand/__manifest__.py
odoo/addons/shopinvader_product_brand/data/ir_export_brand.xml
odoo/addons/shopinvader_product_brand/data/ir_export_product.xml
odoo/addons/shopinvader_product_brand/i18n/shopinvader_product_brand.pot
odoo/addons/shopinvader_product_brand/models/__init__.py
odoo/addons/shopinvader_product_brand/models/product_brand.py
odoo/addons/shopinvader_product_brand/models/shopinvader_backend.py
odoo/addons/shopinvader_product_brand/models/shopinvader_brand.py
odoo/addons/shopinvader_product_brand/models/shopinvader_product.py
odoo/addons/shopinvader_product_brand/readme/CONTRIBUTORS.rst
odoo/addons/shopinvader_product_brand/readme/DESCRIPTION.rst
odoo/addons/shopinvader_product_brand/security/ir.model.access.csv
odoo/addons/shopinvader_product_brand/static/description/index.html
odoo/addons/shopinvader_product_brand/tests/__init__.py
odoo/addons/shopinvader_product_brand/tests/common.py
odoo/addons/shopinvader_product_brand/tests/test_brand.py
odoo/addons/shopinvader_product_brand/views/product_brand_view.xml
odoo/addons/shopinvader_product_brand/views/shopinvader_backend_view.xml
odoo/addons/shopinvader_product_brand/views/shopinvader_brand_view.xml
odoo14_addon_shopinvader_product_brand-14.0.1.3.1.dist-info/METADATA
odoo14_addon_shopinvader_product_brand-14.0.1.3.1.dist-info/WHEEL
odoo14_addon_shopinvader_product_brand-14.0.1.3.1.dist-info/top_level.txt
odoo14_addon_shopinvader_product_brand-14.0.1.3.1.dist-info/RECORD
